Workbook
Name Aporte_investimento: 'APP - Controle de Investimento'!$C$18
Name Dividendos: 'APP - Controle de Investimento'!$C$22
Name Patrimônio: 'APP - Controle de Investimento'!$C$21
Name QTD_anos: 'APP - Controle de Investimento'!$C$19
Name Rendimento_carteira: 'APP - Controle de Investimento'!$E$13
Name Salario: 'APP - Controle de Investimento'!$B$12
Name Sugestao_invest.: 'APP - Controle de Investimento'!$B$14
Name Taxa_mensal: 'APP - Controle de Investimento'!$C$20

Sheet APP - Controle de Investimento
B10: CONFIGURAÇÕES
B12: Salário | E12: 5107
B13: Rendimento carteira | E13: 0.009
B14: Sugestão de Investimento (30%) | E14: =E12*30% -> 1532.1
B16: INVESTIMENTO MENSAL
B18: Quanto investir por mês? | C18: 1532.1
B19: Por quantos anos? | C19: 10
B20: Taxa de rendimento mensal? | C20: 0.0108
B21: Patrimônio acumulado? | C21: =FV(Taxa_mensal,QTD_anos*12,Aporte_investimento*-1) -> 373001.49
B22: Dividendos mensais? | C22: =Patrimônio*Rendimento_carteira -> 3357.0134
B24: CENÁRIOS | F24: DIVIDENDOS
A26: 2 | B26: Quanto eu teria em 2 anos? | C26: =FV($C$20,$A26*12,$C$18*-1) -> 41720.406 | F26: =C26*Rendimento_carteira -> 375.48366
A27: 5 | B27: Quanto eu teria em 5 anos? | C27: =FV($C$20,$A27*12,$C$18*-1) -> 128396.14 | F27: =C27*Rendimento_carteira -> 1155.5652
A28: 10 | B28: Quanto eu teria em 10 anos? | C28: =FV($C$20,$A28*12,$C$18*-1) -> 373001.49 | F28: =C28*Rendimento_carteira -> 3357.0134
A29: 20 | B29: Quanto eu teria em 20 anos? | C29: =FV($C$20,$A29*12,$C$18*-1) -> 1726751.8 | F29: =C29*Rendimento_carteira -> 15540.766
A30: 30 | B30: Quanto eu teria em 30 anos? | C30: =FV($C$20,$A30*12,$C$18*-1) -> 6639975.6 | F30: =C30*Rendimento_carteira -> 59759.78
B33: PERFIL | C33: AGRESSIVO
B34: VALOR A SER INVESTIDO POR MÊS | D34: 1260
B36: TIPO DE FII | D36: Percentual Sugerido | F36: Valores
B37: PAPEL | D37: =VLOOKUP($C$33&"-"&TRIM(B37),'Tabela de Apoio'!$A$3:$D$20,4,FALSE()) -> 0.5 | F37: =D37*$D$34 -> 630
B38: TIJOLO | D38: =VLOOKUP($C$33&"-"&TRIM(B38),'Tabela de Apoio'!$A$3:$D$20,4,FALSE()) -> 0.1 | F38: =D38*$D$34 -> 126
B39: HÍBRIDOS | D39: =VLOOKUP($C$33&"-"&TRIM(B39),'Tabela de Apoio'!$A$3:$D$20,4,FALSE()) -> 0.05 | F39: =D39*$D$34 -> 63
B40: FOFs | D40: =VLOOKUP($C$33&"-"&TRIM(B40),'Tabela de Apoio'!$A$3:$D$20,4,FALSE()) -> 0.05 | F40: =D40*$D$34 -> 63
B41: DESENVOLVIMENTO | D41: =VLOOKUP($C$33&"-"&TRIM(B41),'Tabela de Apoio'!$A$3:$D$20,4,FALSE()) -> 0.2 | F41: =D41*$D$34 -> 252
B42: HOTELARIAS | D42: =VLOOKUP($C$33&"-"&TRIM(B42),'Tabela de Apoio'!$A$3:$D$20,4,FALSE()) -> 0.1 | F42: =D42*$D$34 -> 126
F43: =SUM(F37:F42) -> 1260

Sheet Tabela de Apoio
A2: CHAVE | B2: PERFIL | C2: TIPO DE FII | D2: %
A3: =B3&"-"&C3 -> CONSERVADOR-PAPEL | B3: CONSERVADOR | C3: PAPEL | D3: 0.3
A4: =B4&"-"&C4 -> CONSERVADOR-TIJOLO | B4: CONSERVADOR | C4: TIJOLO | D4: 0.5
A5: =B5&"-"&C5 -> CONSERVADOR-HÍBRIDOS | B5: CONSERVADOR | C5: HÍBRIDOS | D5: 0.1
A6: =B6&"-"&C6 -> CONSERVADOR-FOFs | B6: CONSERVADOR | C6: FOFs | D6: 0.1
A7: =B7&"-"&C7 -> CONSERVADOR-DESENVOLVIMENTO | B7: CONSERVADOR | C7: DESENVOLVIMENTO | D7: 0
A8: =B8&"-"&C8 -> CONSERVADOR-HOTELARIAS | B8: CONSERVADOR | C8: HOTELARIAS | D8: 0
A9: =B9&"-"&C9 -> MODERADO-PAPEL | B9: MODERADO | C9: PAPEL | D9: 0.32
A10: =B10&"-"&C10 -> MODERADO-TIJOLO | B10: MODERADO | C10: TIJOLO | D10: 0.35
A11: =B11&"-"&C11 -> MODERADO-HÍBRIDOS | B11: MODERADO | C11: HÍBRIDOS | D11: 0.08
A12: =B12&"-"&C12 -> MODERADO-FOFs | B12: MODERADO | C12: FOFs | D12: 0.05
A13: =B13&"-"&C13 -> MODERADO-DESENVOLVIMENTO | B13: MODERADO | C13: DESENVOLVIMENTO | D13: 0.1
A14: =B14&"-"&C14 -> MODERADO-HOTELARIAS | B14: MODERADO | C14: HOTELARIAS | D14: 0.1
... A20: =B20&"-"&C20 -> AGRESSIVO-HOTELARIAS | B20: AGRESSIVO | C20: HOTELARIAS | D20: 0.1
